rechistoso/__init__.py
rechistoso/cli.py
rechistoso/test/__init__.py
rechistoso/test/test_chiste.py
rechistoso-0.2.1.dist-info/DESCRIPTION.rst
rechistoso-0.2.1.dist-info/METADATA
rechistoso-0.2.1.dist-info/RECORD
rechistoso-0.2.1.dist-info/WHEEL
rechistoso-0.2.1.dist-info/entry_points.txt
rechistoso-0.2.1.dist-info/metadata.json
rechistoso-0.2.1.dist-info/top_level.txt
