Metadata-Version: 2.0
Name: rechistoso
Version: 0.2.1
Summary: Un chiste rechistoso
Home-page: UNKNOWN
Author: Luciano Serruya Aloisi
Author-email: lucianoserruya@gmail.com
License: MIT
Keywords: chiste gracioso muybueno bueno funny joke good really funniest
Platform: UNKNOWN
